{
  "$schema": "https://zjv.ch/nav.schema.json",
  "nav": [
    { "label": "News",  "href": "/news" },
    { 
      "label": "Kurse", 
      "href": "/kurse",
      "children": [
        { "label": "Kurse",       "href": "/kurse" },
        { "label": "SV / pa!!as", "href": "https://www.pallas.ch/kursangebote/kursangebote.html" }
      ]
    },
    {
      "label": "Leistungssport",
      "href": "/leistungssport",
      "children": [
        { "label": "RLZ",              "href": "https://rlz-zjv.ch/" },
        { "label": "Kantonalkader",    "href": "http://zjv-kantonalkader.clubdesk.com/clubdesk/www" },
        { "label": "Behindertensport", "href": "/leistungssport/zjv-behindertensport" }
      ]
    },
    {
      "label": "ZJV",
      "href": "/zjv",
      "children": [
        { "label": "Vorstellung",     "href": "/zjv/vorstellung" },
        { "label": "Verantwortliche", "href": "/zjv/personen" },
        { "label": "Mitgliedschaften","href": "/zjv/mitgliedschaften" }
      ]
    }
  ]
}
